README.md
setup.py
tests/__init__.py
tests/backtests/__init__.py
tests/backtests/backtest_author_trades.py
tests/backtests/backtest_recent_trades.py
tests/backtests/backtests.py
tests/prompt_tests/__init__.py
tests/prompt_tests/open_or_close_prompt_test.py
tests/prompt_tests/prompt_tests_old.py
tests/prompt_tests/prompt_tests_with_validation_data.py
tests/unit/__init__.py
tests/unit/response_parsers.py
tests/unit/rule_based_classifier_tests.py
tests/unit/tweet_symbol_parsing_tests.py
tests/unit/tweet_trade_parsing_tests.py
tests/unit/backtest/__init__.py
tests/unit/backtest/binance_mapping_tests.py
tests/unit/backtest/trades/__init__.py
tests/unit/backtest/trades/backtest_curated_trades.py
trader_tweets/__init__.py
trader_tweets/prompt_factory.py
trader_tweets/trade_tweet_job.py
trader_tweets/tweet_parsing.py
trader_tweets.egg-info/PKG-INFO
trader_tweets.egg-info/SOURCES.txt
trader_tweets.egg-info/dependency_links.txt
trader_tweets.egg-info/requires.txt
trader_tweets.egg-info/top_level.txt
trader_tweets/model/__init__.py
trader_tweets/model/classified_tweet.py
trader_tweets/model/db_classified_tweet.py
trader_tweets/model/trade.py
trader_tweets/model/tweet_mood.py
trader_tweets/model/tweet_type.py
trader_tweets/model/prompt/__init__.py
trader_tweets/model/prompt/bullish_bearish.py
trader_tweets/model/prompt/buying_selling.py
trader_tweets/model/prompt/prompt.py
trader_tweets/model/twitter/__init__.py
trader_tweets/model/twitter/simple_tweet.py
trader_tweets/model/twitter/twitter_traders.py
trader_tweets/model/twitter/twitter_user.py
trader_tweets/repository/__init__.py
trader_tweets/repository/binance_repository.py
trader_tweets/repository/classified_tweets_repository.py
trader_tweets/repository/gpt_repository.py
trader_tweets/repository/secret_repository.py
trader_tweets/repository/twitter/__init__.py
trader_tweets/repository/twitter/twitter_api_repository.py
trader_tweets/repository/twitter/twitter_repository.py
trader_tweets/repository/twitter/twscrape_repository.py
trader_tweets/service/__init__.py
trader_tweets/service/binance_service.py
trader_tweets/service/cache_service.py
trader_tweets/service/discord_service.py
